Images/__init__.py
Images/overview.png
Resources/__init__.py
Resources/frequency_dict_n_grams_1.pickle
Resources/go.obo.pickle_dict
Resources/go.obo.pickle_syns
Resources/go.obo.pickle_terms
Resources/verbs.tab
Resources/verbs_set.pickle
Workflows/__init__.py
Workflows/Representative_function/Cluster_Representative_Function.py
Workflows/Representative_function/README.md
Workflows/Representative_function/__init__.py
Workflows/Representative_function/test.tsv
unifunc/__init__.py
unifunc/__main__.py
unifunc/source.py
UniFunc-1.3.dist-info/LICENSE
UniFunc-1.3.dist-info/METADATA
UniFunc-1.3.dist-info/WHEEL
UniFunc-1.3.dist-info/entry_points.txt
UniFunc-1.3.dist-info/top_level.txt
UniFunc-1.3.dist-info/RECORD
